idds/__init__.py
idds/client/__init__.py
idds/client/authclient.py
idds/client/base.py
idds/client/cacherclient.py
idds/client/catalogclient.py
idds/client/client.py
idds/client/clientmanager.py
idds/client/hpoclient.py
idds/client/logsclient.py
idds/client/messageclient.py
idds/client/pingclient.py
idds/client/requestclient.py
idds/client/version.py
idds_client-2.0.9.data/data/etc/idds/idds.cfg.client.template
idds_client-2.0.9.data/data/tools/env/environment.yml
idds_client-2.0.9.data/scripts/idds
idds_client-2.0.9.dist-info/LICENSE.rst
idds_client-2.0.9.dist-info/METADATA
idds_client-2.0.9.dist-info/WHEEL
idds_client-2.0.9.dist-info/top_level.txt
idds_client-2.0.9.dist-info/RECORD
